topsis/__init__.py
topsis/__main__.py
topsis_102103411/__init__.py
topsis_102103411/__main__.py
topsis_102103411-1.1.0.dist-info/LICENSE
topsis_102103411-1.1.0.dist-info/METADATA
topsis_102103411-1.1.0.dist-info/WHEEL
topsis_102103411-1.1.0.dist-info/entry_points.txt
topsis_102103411-1.1.0.dist-info/top_level.txt
topsis_102103411-1.1.0.dist-info/RECORD
