Metadata-Version: 2.1
Name: topsis-102103411
Version: 1.1.0
Summary: Topsis
Author: Harshit Goyal
Author-email: hgoyal1_be21@thapar.edu
License: MIT
Classifier: License :: OSI Approved :: MIT License
Classifier: Programming Language :: Python :: 3.6
Classifier: Programming Language :: Python :: 3.7
Classifier: Programming Language :: Python :: 3.8
License-File: LICENSE
